src/__init__.py
short_activist_pred-1.0.0.dist-info/LICENSE.txt
short_activist_pred-1.0.0.dist-info/METADATA
short_activist_pred-1.0.0.dist-info/WHEEL
short_activist_pred-1.0.0.dist-info/top_level.txt
short_activist_pred-1.0.0.dist-info/RECORD
