Metadata-Version: 2.1
Name: short-activist-pred
Version: 1.0.0
Summary: Short activists prediction
Home-page: https://github.com/DanGlChris/short-activist-pred
Author: Daglox Kankwanda
Author-email: dagloxkankwenda@gmail.com
License: MIT
Project-URL: Documentation, https://pyscaffold.org/
Platform: any
Classifier: Development Status :: 4 - Beta
Classifier: Programming Language :: Python
License-File: LICENSE.txt
Requires-Dist: bertopic (>=0.15.0)
Requires-Dist: pdfplumber (>=0.10.2)
Requires-Dist: numpy (>=1.20.0)
Requires-Dist: pandas (>=1.1.5)
Requires-Dist: matplotlib (>=3.1.7)
Requires-Dist: re
Requires-Dist: string
Requires-Dist: nltk (>=3.8.1)
Requires-Dist: wordcloud (>=1.9.2)
Requires-Dist: tkinter
Requires-Dist: transformers (>=4.34.0)
Requires-Dist: huggingface-hub (>=3.0.4)
Requires-Dist: pwinput
Provides-Extra: testing
Requires-Dist: setuptools ; extra == 'testing'
Requires-Dist: pytest ; extra == 'testing'
Requires-Dist: pytest-cov ; extra == 'testing'
